stylometry_ttr/__init__.py
stylometry_ttr/models.py
stylometry_ttr/py.typed
stylometry_ttr/tokenizer.py
stylometry_ttr/ttr.py
stylometry_ttr-1.0.3.dist-info/LICENSE
stylometry_ttr-1.0.3.dist-info/METADATA
stylometry_ttr-1.0.3.dist-info/WHEEL
stylometry_ttr-1.0.3.dist-info/RECORD
