Metadata-Version: 2.1
Name: stylometry-ttr
Version: 1.0.3
Summary: Type-Token Ratio (TTR) computation for stylometric analysis
License: MIT
Keywords: stylometry,ttr,type-token-ratio,nlp,linguistics,text-analysis,vocabulary
Author: Craig Trim
Author-email: ctrim@maryville.edu
Requires-Python: >=3.11,<4.0
Classifier: Intended Audience :: Developers
Classifier: Intended Audience :: Science/Research
Classifier: License :: OSI Approved :: MIT License
Classifier: Programming Language :: Python :: 3
Classifier: Programming Language :: Python :: 3.11
Classifier: Programming Language :: Python :: 3.12
Classifier: Topic :: Scientific/Engineering :: Information Analysis
Classifier: Topic :: Text Processing :: Linguistic
Classifier: Typing :: Typed
Requires-Dist: pydantic (>=2.5,<3.0)
Project-URL: Documentation, https://github.com/craigtrim/stylometry-ttr/blob/main/docs/API.md
Project-URL: Homepage, https://github.com/craigtrim/stylometry-ttr
Project-URL: Repository, https://github.com/craigtrim/stylometry-ttr
